Metadata-Version: 1.1
Name: ShellQuery
Version: 0.1.4
Summary: Command line plain text SQL
Home-page: https://github.com/jingw/shellquery
Author: Jing Wang
Author-email: 99jingw@gmail.com
License: MIT License
Platform: UNKNOWN
Classifier: Environment :: Console
Classifier: Intended Audience :: Developers
Classifier: Intended Audience :: System Administrators
Classifier: License :: OSI Approved :: MIT License
Classifier: Operating System :: OS Independent
Classifier: Programming Language :: Python
Classifier: Programming Language :: Python :: 2
Classifier: Programming Language :: Python :: 3
Classifier: Programming Language :: SQL
Classifier: Topic :: Text Processing
Classifier: Topic :: Utilities
